binaryreader.cpython-39-darwin.so
binaryreader-0.1.4.dist-info/LICENSE
binaryreader-0.1.4.dist-info/METADATA
binaryreader-0.1.4.dist-info/WHEEL
binaryreader-0.1.4.dist-info/top_level.txt
binaryreader-0.1.4.dist-info/RECORD
